README.md
README.rst
setup.py
keras_bert/__init__.py
keras_bert/bert.py
keras_bert/loader.py
keras_bert/tpu_support.py
keras_bert/layers/__init__.py
keras_bert/layers/dense.py
keras_bert/layers/embedding.py
keras_bert/layers/extract.py
keras_bert/layers/feed_forward.py
keras_bert/layers/inputs.py
keras_bert/layers/layer_normalization.py
keras_bert/layers/masked.py
keras_bert/layers/multi_head_attention.py
keras_bert/layers/transformer.py
keras_bert_tpu.egg-info/PKG-INFO
keras_bert_tpu.egg-info/SOURCES.txt
keras_bert_tpu.egg-info/dependency_links.txt
keras_bert_tpu.egg-info/requires.txt
keras_bert_tpu.egg-info/top_level.txt
tests/__init__.py
tests/test_bert.py
tests/test_loader.py
tests/layers/__init__.py
tests/layers/test_embedding.py
tests/layers/test_extract.py
tests/layers/test_inputs.py
tests/layers/test_masked.py