Metadata-Version: 1.1
Name: keras-bert-tpu
Version: 0.1.6
Summary: BERT implemented in Keras of Tensorflow package on TPU
Home-page: https://github.com/HighCWu/keras-bert-tpu
Author: HighCWu
Author-email: HighCWu@163.com
License: MIT
Platform: UNKNOWN
Classifier: Programming Language :: Python :: 2.7
Classifier: Programming Language :: Python :: 3.6
Classifier: License :: OSI Approved :: MIT License
Classifier: Operating System :: OS Independent
